myray/__init__.py
myray/context.py
myray-0.1.1.dist-info/METADATA
myray-0.1.1.dist-info/WHEEL
myray-0.1.1.dist-info/top_level.txt
myray-0.1.1.dist-info/RECORD
